RsFsw
